myonotify/__init__.py
myonotify-1.1.dist-info/METADATA
myonotify-1.1.dist-info/WHEEL
myonotify-1.1.dist-info/top_level.txt
myonotify-1.1.dist-info/zip-safe
myonotify-1.1.dist-info/RECORD
